{
  "title": "<span class=\"text-blue-600 dark:text-blue-400 text-xl font-bold\">حقيقة:</span> اللعب ومشاهدة الأفلام أثناء شحن الهاتف: هل يدمر البطارية فعلاً؟",
  "slug": "Playing-Destroy-Battery",
  "description": "تعرف على التفسير العلمي حول استخدام الهاتف الذكي أثناء الشحن. هل يستهلك الهاتف طاقة البطارية أم الشاحن؟ وكيف تؤثر الألعاب ومشاهدة الأفلام على عمر بطاريتك.",
  "category": "articles",
  "date": "2026-03-11",
  "time": "15:40",
  "image": "https://cdn.jsdelivr.net/gh/kinanmjeed88/kinantouch.com.apk@main/images/assets/images/1773232907674_٢٠٢٦٠٣١١_٠٢٣١٠٠.webp",
  "content": "<div class=\"font-[Tajawal] text-[16px] leading-8 text-gray-900 dark:text-gray-100 space-y-8\">\n\n    <div class=\"bg-gradient-to-r from-blue-900 to-indigo-800 rounded-2xl p-6 text-white shadow-lg mb-8 relative overflow-hidden\">\n        <i class=\"fas fa-gamepad absolute -bottom-4 -left-4 text-white/10 text-9xl transform -rotate-12\"></i>\n        <div class=\"relative z-10\">\n            <h2 class=\"text-2xl font-black mb-3 flex items-center gap-2\">\n                <i class=\"fas fa-battery-bolt text-yellow-400\"></i> اللعب أثناء الشحن: تدمير للبطارية أم خرافة تقنية؟\n            </h2>\n            <p class=\"text-blue-100 m-0 text-lg leading-relaxed\">\n                هل يتغذى الهاتف من البطارية أم من الشاحن عندما تلعب أثناء توصيله بالكهرباء؟ وهل استخدام الهاتف أثناء الشحن يتلف البطارية حقاً؟ إليك التفسير العلمي القاطع بعيداً عن التكهنات.\n            </p>\n        </div>\n    </div>\n\n    <section class=\"bg-gray-50 dark:bg-slate-800/50 border border-gray-200 dark:border-slate-700 rounded-xl p-6 shadow-sm\">\n        <h3 class=\"font-bold text-xl text-gray-800 dark:text-white mb-4 flex items-center gap-2 border-b border-gray-200 dark:border-slate-700 pb-3\">\n            <i class=\"fas fa-microchip text-blue-500\"></i> من أين يستمد الهاتف طاقته عند الشحن والاستخدام معاً؟\n        </h3>\n        <p class=\"text-gray-700 dark:text-gray-300 m-0 leading-relaxed\">\n            الاعتقاد بأن البطارية \"تشحن وتفرغ\" في نفس اللحظة هو أمر مستحيل فيزيائياً. الهواتف الحديثة مزودة بشريحة ذكية لإدارة الطاقة <span class=\"font-bold text-blue-600 dark:text-blue-400 text-sm bg-blue-50 dark:bg-blue-900/30 px-2 py-1 rounded\">(PMIC)</span>. عند توصيل الشاحن، يقوم النظام <strong>بتوجيه طاقة الشاحن لتشغيل الهاتف (المعالج والشاشة) أولاً</strong>، وما يتبقى من طاقة الشاحن يتم توجيهه لتعبئة البطارية. إذن، أنت تستخدم طاقة الشاحن المباشرة وليس البطارية.\n        </p>\n    </section>\n\n    <div class=\"grid grid-cols-1 md:grid-cols-2 gap-6 my-8\">\n        <div class=\"bg-red-50 dark:bg-red-900/10 border-t-4 border-red-500 rounded-b-xl p-6 shadow-sm\">\n            <div class=\"flex items-center gap-2 mb-3\">\n                <span class=\"bg-red-500 text-white w-8 h-8 flex justify-center items-center rounded-full shadow-sm\">\n                    <i class=\"fas fa-times\"></i>\n                </span>\n                <h4 class=\"font-bold text-lg text-red-800 dark:text-red-400 m-0\">الخرافة الشائعة</h4>\n            </div>\n            <p class=\"text-gray-700 dark:text-gray-300 text-sm leading-relaxed m-0\">\n                \"استخدام الهاتف أثناء الشحن يدمر البطارية لأنها تُستهلك وتُشحن في نفس الوقت، مما يرهق الخلايا الكيميائية ويؤدي إلى انتفاخها أو تلفها بسرعة.\"\n            </p>\n        </div>\n\n        <div class=\"bg-emerald-50 dark:bg-emerald-900/10 border-t-4 border-emerald-500 rounded-b-xl p-6 shadow-sm\">\n            <div class=\"flex items-center gap-2 mb-3\">\n                <span class=\"bg-emerald-500 text-white w-8 h-8 flex justify-center items-center rounded-full shadow-sm\">\n                    <i class=\"fas fa-check\"></i>\n                </span>\n                <h4 class=\"font-bold text-lg text-emerald-800 dark:text-emerald-400 m-0\">الحقيقة العلمية</h4>\n            </div>\n            <p class=\"text-gray-700 dark:text-gray-300 text-sm leading-relaxed m-0\">\n                القاتل الحقيقي للبطارية هو <strong>\"الحرارة\"</strong> وليس مسار الطاقة. الألعاب الثقيلة أثناء الشحن تجمع بين حرارة المعالج وحرارة الشحن، وهذا الإجهاد الحراري المزدوج هو ما يسرع من تدهور عمر البطارية.\n            </p>\n        </div>\n    </div>\n\n    <section class=\"my-8\">\n        <h3 class=\"font-bold text-xl text-gray-800 dark:text-white mb-5 flex items-center gap-2\">\n            <i class=\"fas fa-balance-scale text-indigo-500\"></i> هل يختلف الأمر بين الألعاب ومشاهدة الأفلام؟\n        </h3>\n        \n        <div class=\"space-y-4\">\n            <div class=\"flex items-start gap-4 p-4 bg-white dark:bg-slate-900 border border-gray-200 dark:border-slate-700 rounded-xl hover:border-blue-300 transition-colors\">\n                <div class=\"bg-blue-100 dark:bg-blue-900/50 text-blue-600 dark:text-blue-400 p-3 rounded-lg text-2xl\">\n                    <i class=\"fas fa-film\"></i>\n                </div>\n                <div>\n                    <h4 class=\"font-bold text-gray-800 dark:text-white mb-1\">مشاهدة الأفلام وتصفح السوشيال ميديا</h4>\n                    <p class=\"text-sm text-gray-600 dark:text-gray-400 m-0 leading-relaxed\">\n                        مهام خفيفة لا تضغط على المعالج، وبالتالي لا تولد حرارة تذكر. <strong>النتيجة:</strong> استخدام الهاتف لهذه المهام أثناء الشحن آمن تماماً ولا يسبب تدهوراً إضافياً للبطارية.\n                    </p>\n                </div>\n            </div>\n\n            <div class=\"flex items-start gap-4 p-4 bg-white dark:bg-slate-900 border border-gray-200 dark:border-slate-700 rounded-xl hover:border-orange-300 transition-colors\">\n                <div class=\"bg-orange-100 dark:bg-orange-900/50 text-orange-600 dark:text-orange-400 p-3 rounded-lg text-2xl\">\n                    <i class=\"fas fa-fire-alt\"></i>\n                </div>\n                <div>\n                    <h4 class=\"font-bold text-gray-800 dark:text-white mb-1\">لعب الألعاب الثقيلة (مثل ببجي وكول أوف ديوتي)</h4>\n                    <p class=\"text-sm text-gray-600 dark:text-gray-400 m-0 leading-relaxed\">\n                        مهام تستهلك أقصى طاقة للمعالج (توليد حرارة) + عملية الشحن السريع (توليد حرارة). <strong>النتيجة:</strong> حرارة مضاعفة تتسبب في تدهور كيميائي سريع لخلايا الليثيوم. من الأفضل فصل الشاحن أثناء اللعب للحفاظ على عمر البطارية.\n                    </p>\n                </div>\n            </div>\n        </div>\n    </section>\n\n    <div class=\"bg-gray-100 dark:bg-slate-800 p-6 rounded-2xl border-l-4 border-indigo-500 mt-10 shadow-sm\">\n        <h3 class=\"font-black text-lg text-gray-800 dark:text-white mb-3 flex items-center gap-2\">\n            <i class=\"fas fa-clipboard-check text-indigo-500\"></i> الخلاصة المباشرة (القاعدة الذهبية):\n        </h3>\n        <ul class=\"space-y-2 text-gray-700 dark:text-gray-300 text-sm list-disc list-inside marker:text-indigo-500\">\n            <li>الهاتف يستخدم <strong>طاقة الشاحن</strong> لتشغيل نفسه أثناء التوصيل، ويشحن البطارية بالفائض.</li>\n            <li>الاستخدام الخفيف (أفلام، تصفح، يوتيوب) أثناء الشحن <strong>آمن تماماً</strong>.</li>\n            <li>الاستخدام الثقيل (الألعاب، تصوير فيديو 4K) أثناء الشحن <strong>يضر البطارية</strong> بسبب الحرارة العالية وليس بسبب الاستهلاك المزدوج.</li>\n            <li><strong>نصيحة تقنية:</strong> إذا كنت مضطراً للعب، انزع غلاف الهاتف (الكفر) لتشتيت الحرارة، أو استخدم هواتف الألعاب التي تدعم ميزة <strong>Bypass Charging</strong> (تجاوز البطارية).</li>\n        </ul>\n    </div>\n\n</div>",
  "youtubeVideoId": "",
  "summary": "### 🚀 الخلاصة في نقاط\n\n* **النقطة الأولى القوية:** الهواتف الحديثة مزودة بشريحة ذكية لإدارة الطاقة (PMIC) التي توجيه طاقة الشاحن لتشغيل الهاتف أولاً ثم تعبئة البطارية.\n* **النقطة الثانية:** استخدام الهاتف أثناء الشحن لا يدمر البطارية، ولكن الاستخدام الثقيل للألعاب يمكن أن يضر البطارية بسبب الحرارة العالية.\n* **النقطة الثالثة:** الاستخدام الخفيف مثل مشاهدة الأفلام أو تصفح السوشيال ميديا أثناء الشحن آمن تماماً ولا يسبب تدهوراً إضافياً للبطارية.\n* **النقطة الرابعة:** إذا كنت مضطراً للعب الألعاب أثناء الشحن، انزع غلاف الهاتف أو استخدم هواتف الألعاب التي تدعم ميزة تجاوز البطارية (Bypass Charging).\n* **النقطة الخامسة:** الحرارة هي القاتل الحقيقي للبطارية، وليس الاستهلاك المزدوج من البطارية والشاحن.",
  "renderMode": "html",
  "id": "Playing-Destroy-Battery"
}